AoV_Zstd/__init__.py
AoV_Zstd-0.0.4.dist-info/LICENSE
AoV_Zstd-0.0.4.dist-info/METADATA
AoV_Zstd-0.0.4.dist-info/WHEEL
AoV_Zstd-0.0.4.dist-info/top_level.txt
AoV_Zstd-0.0.4.dist-info/RECORD
