Metadata-Version: 2.1
Name: AoV_Zstd
Version: 0.0.4
Summary: A tool for de/compressed file AOV/ROV game
Author-email: HoangMS <trungheocs1@gmail.com>
Classifier: Programming Language :: Python :: 3
Classifier: License :: OSI Approved :: MIT License
Classifier: Operating System :: OS Independent
Requires-Python: >=3.8
License-File: LICENSE
Requires-Dist: pyzstd
